LICENSE
MANIFEST.in
README.md
setup.cfg
setup.py
Mopidy_Market.egg-info/PKG-INFO
Mopidy_Market.egg-info/SOURCES.txt
Mopidy_Market.egg-info/dependency_links.txt
Mopidy_Market.egg-info/entry_points.txt
Mopidy_Market.egg-info/not-zip-safe
Mopidy_Market.egg-info/requires.txt
Mopidy_Market.egg-info/top_level.txt
mopidy_market/__init__.py
mopidy_market/ext.conf
mopidy_market/geticons.py
mopidy_market/test.py
mopidy_market/web.py
mopidy_market/static/index.html
mopidy_market/static/icons/alsamixer.png
mopidy_market/static/icons/bandcamp.png
mopidy_market/static/icons/beets.png
mopidy_market/static/icons/dleyna.png
mopidy_market/static/icons/emby.ico
mopidy_market/static/icons/funkwhale.png
mopidy_market/static/icons/funkwhale.svg
mopidy_market/static/icons/internetarchive.png
mopidy_market/static/icons/iris.jpg
mopidy_market/static/icons/jamendo.svg
mopidy_market/static/icons/jellyfin.svg
mopidy_market/static/icons/mixcloud.png
mopidy_market/static/icons/mobile.jpg
mopidy_market/static/icons/mopidy.png
mopidy_market/static/icons/mopster.png
mopidy_market/static/icons/mowecl.png
mopidy_market/static/icons/mpd.png
mopidy_market/static/icons/mpris.png
mopidy_market/static/icons/mpris.svg
mopidy_market/static/icons/muse.jpg
mopidy_market/static/icons/musicbox_darkclient.png
mopidy_market/static/icons/musicbox_webclient.jpg
mopidy_market/static/icons/nad.png
mopidy_market/static/icons/nad.svg
mopidy_market/static/icons/orfradio.png
mopidy_market/static/icons/orfradio.svg
mopidy_market/static/icons/pandora.jpg
mopidy_market/static/icons/party.jpg
mopidy_market/static/icons/podcast-itunes.png
mopidy_market/static/icons/radionet.png
mopidy_market/static/icons/radionet1.png
mopidy_market/static/icons/radionet2.png
mopidy_market/static/icons/somafm.gif
mopidy_market/static/icons/soundcloud.png
mopidy_market/static/icons/spotify.png
mopidy_market/static/icons/subidy.png
mopidy_market/static/icons/tunein.svg
mopidy_market/static/icons/yamusic.svg
mopidy_market/static/icons/youtube.png
mopidy_market/static/icons/ytmusic.png
mopidy_market/static/static/css/main.e8f860c3.css
mopidy_market/static/static/css/main.e8f860c3.css.map
mopidy_market/static/static/js/main.e338471f.js
mopidy_market/static/static/js/main.e338471f.js.LICENSE.txt
